{
    "timestamp": "2022-04-28T23:14:44.347",
    "success": true,
    "code": null,
    "msg": null,
    "data": [
        {
            "rowIndex": 0,
            "success": false,
            "message": null,
            "pageSize": 100,
            "pageNum": 1,
            "lctreMthodNm": "\ub300\uba74",
            "lctrmInfo": "\ub300\ud559\uc6d0\ub3d9",
            "lctreLnggeSctcd": null,
            "crseNo": "CLTR0132-002",
            "estblUnivNm": "\uc778\ubb38\ub300\ud559",
            "estblDprtnNm": "\ub178\uc5b4\ub178\ubb38\ud559\uacfc",
            "estblYear": "2022",
            "estblDprtnCd": "110B",
            "estblSmstrSctnm": "1\ud559\uae30",
            "estblSmstrSctcd": "CMBS001400001",
            "estblGrade": "*",
            "sbjetSctnm": "\uad50\uc591",
            "sbjetNm": "\ub7ec\uc2dc\uc544\ubb38\ud559\uc758 \uc774\ud574",
            "sbjetDvnno": "002",
            "sbjetCd": "CLTR0132",
            "gubun": null,
            "pckgeRqstPssblYn": "Y",
            "pckgeRqstCnt": "8",
            "name": null,
            "rmrk": "\uc804\ud559\ub144\uc120\ud0dd<br><b>\uc778\ubb38\uad50\uc591</b><br>",
            "appcrCnt": "20",
            "attlcPrscpCnt": "70",
            "lssnsTimeInfo": "\ud654 2B,3A,3B<br/>\ubaa9 1A,1B,2A",
            "lssnsRealTimeInfo": "\ud654 10:30 ~ 12:00<br/>\ubaa9 09:00 ~ 10:30",
            "prctsTime": "0",
            "doPlan": "Kor",
            "thryTime": "3",
            "totalPrfssNm": "\uc774\uac15\uc740",
            "mngetEstblYn": "Y",
            "code": null,
            "crdit": "3",
            "expniSllbsYn": "Y",
            "bldngSn": null,
            "bldngCd": null,
            "bldngNm": null,
            "lssnsLcttmUntcd": null,
            "sbjetSctcd2": null,
            "rmnmCd": "203",
            "isApi": null,
            "paging": false,
            "rowStatus": "R",
            "pageSort": null
        },
        {
            "rowIndex": 0,
            "success": false,
            "message": null,
            "pageSize": 100,
            "pageNum": 1,
            "lctreMthodNm": "\ub300\uba74",
            "lctrmInfo": "\uc778\ubb38\ub300\ud559",
            "lctreLnggeSctcd": null,
            "crseNo": "CLTR0036-002",
            "estblUnivNm": "\uc778\ubb38\ub300\ud559",
            "estblDprtnNm": "\ub178\uc5b4\ub178\ubb38\ud559\uacfc",
            "estblYear": "2022",
            "estblDprtnCd": "110B",
            "estblSmstrSctnm": "1\ud559\uae30",
            "estblSmstrSctcd": "CMBS001400001",
            "estblGrade": "*",
            "sbjetSctnm": "\uad50\uc591",
            "sbjetNm": "\ub7ec\uc2dc\uc544\uc5b4 I",
            "sbjetDvnno": "002",
            "sbjetCd": "CLTR0036",
            "gubun": null,
            "pckgeRqstPssblYn": "Y",
            "pckgeRqstCnt": "19",
            "name": null,
            "rmrk": "\uc804\ud559\ub144\uc120\ud0dd<br><b>\uc778\ubb38\uad50\uc591</b><br>",
            "appcrCnt": "41",
            "attlcPrscpCnt": "50",
            "lssnsTimeInfo": "\uc6d4 7A,7B,8A<br/>\uae08 7A,7B,8A",
            "lssnsRealTimeInfo": "\uc6d4 15:00 ~ 16:30<br/>\uae08 15:00 ~ 16:30",
            "prctsTime": "0",
            "doPlan": "Kor",
            "thryTime": "3",
            "totalPrfssNm": "\uc815\uc9c0\uc724",
            "mngetEstblYn": "Y",
            "code": null,
            "crdit": "3",
            "expniSllbsYn": "N",
            "bldngSn": null,
            "bldngCd": null,
            "bldngNm": null,
            "lssnsLcttmUntcd": null,
            "sbjetSctcd2": null,
            "rmnmCd": "308",
            "isApi": null,
            "paging": false,
            "rowStatus": "R",
            "pageSort": null
        },
        {
            "rowIndex": 0,
            "success": false,
            "message": null,
            "pageSize": 100,
            "pageNum": 1,
            "lctreMthodNm": "\ub300\uba74",
            "lctrmInfo": "\uc778\ubb38\ud55c\uad6d\uc9c4\ud765\uad00",
            "lctreLnggeSctcd": null,
            "crseNo": "CLTR0613-001",
            "estblUnivNm": "\uc778\ubb38\ub300\ud559",
            "estblDprtnNm": "\ub178\uc5b4\ub178\ubb38\ud559\uacfc",
            "estblYear": "2022",
            "estblDprtnCd": "110B",
            "estblSmstrSctnm": "1\ud559\uae30",
            "estblSmstrSctcd": "CMBS001400001",
            "estblGrade": "*",
            "sbjetSctnm": "\uad50\uc591",
            "sbjetNm": "\ub3d9\uc11c\uace0\uc804\uc758 \ub9cc\ub0a8",
            "sbjetDvnno": "001",
            "sbjetCd": "CLTR0613",
            "gubun": null,
            "pckgeRqstPssblYn": "Y",
            "pckgeRqstCnt": "8",
            "name": null,
            "rmrk": "\uc804\ud559\ub144\uc120\ud0dd<br><b>\uc778\ubb38\uad50\uc591</b><br>",
            "appcrCnt": "17",
            "attlcPrscpCnt": "70",
            "lssnsTimeInfo": "\ud654 2B,3A,3B<br/>\ubaa9 1A,1B,2A",
            "lssnsRealTimeInfo": "\ud654 10:30 ~ 12:00<br/>\ubaa9 09:00 ~ 10:30",
            "prctsTime": "0",
            "doPlan": "Kor",
            "thryTime": "3",
            "totalPrfssNm": "\uae40\uaddc\uc885",
            "mngetEstblYn": "Y",
            "code": null,
            "crdit": "3",
            "expniSllbsYn": "N",
            "bldngSn": null,
            "bldngCd": null,
            "bldngNm": null,
            "lssnsLcttmUntcd": null,
            "sbjetSctcd2": null,
            "rmnmCd": "104",
            "isApi": null,
            "paging": false,
            "rowStatus": "R",
            "pageSort": null
        },
        {
            "rowIndex": 0,
            "success": false,
            "message": null,
            "pageSize": 100,
            "pageNum": 1,
            "lctreMthodNm": "\ube44\ub300\uba74",
            "lctrmInfo": "\uc778\ubb38\ud55c\uad6d\uc9c4\ud765\uad00",
            "lctreLnggeSctcd": null,
            "crseNo": "CLTR0643-001",
            "estblUnivNm": "\uc778\ubb38\ub300\ud559",
            "estblDprtnNm": "\ub178\uc5b4\ub178\ubb38\ud559\uacfc",
            "estblYear": "2022",
            "estblDprtnCd": "110B",
            "estblSmstrSctnm": "1\ud559\uae30",
            "estblSmstrSctcd": "CMBS001400001",
            "estblGrade": "*",
            "sbjetSctnm": "\uad50\uc591",
            "sbjetNm": "\uacf5\uc5f0\uc608\uc220\uc758 \uc774\ud574",
            "sbjetDvnno": "001",
            "sbjetCd": "CLTR0643",
            "gubun": null,
            "pckgeRqstPssblYn": "Y",
            "pckgeRqstCnt": "169",
            "name": null,
            "rmrk": "\uc804\ud559\ub144\uc120\ud0dd<br>",
            "appcrCnt": "82",
            "attlcPrscpCnt": "70",
            "lssnsTimeInfo": "\ud654 7A,7B,8A<br/>\ubaa9 7A,7B,8A",
            "lssnsRealTimeInfo": "\ud654 15:00 ~ 16:30<br/>\ubaa9 15:00 ~ 16:30",
            "prctsTime": "0",
            "doPlan": "Kor",
            "thryTime": "3",
            "totalPrfssNm": "\uc774\uc2b9\uc5b5",
            "mngetEstblYn": "Y",
            "code": null,
            "crdit": "3",
            "expniSllbsYn": "N",
            "bldngSn": null,
            "bldngCd": null,
            "bldngNm": null,
            "lssnsLcttmUntcd": null,
            "sbjetSctcd2": null,
            "rmnmCd": "104",
            "isApi": null,
            "paging": false,
            "rowStatus": "R",
            "pageSort": null
        },
        {
            "rowIndex": 0,
            "success": false,
            "message": null,
            "pageSize": 100,
            "pageNum": 1,
            "lctreMthodNm": "\ub300\uba74",
            "lctrmInfo": "\ub300\ud559\uc6d0\ub3d9",
            "lctreLnggeSctcd": null,
            "crseNo": "RUSS0316-002",
            "estblUnivNm": "\uc778\ubb38\ub300\ud559",
            "estblDprtnNm": "\ub178\uc5b4\ub178\ubb38\ud559\uacfc",
            "estblYear": "2022",
            "estblDprtnCd": "110B",
            "estblSmstrSctnm": "1\ud559\uae30",
            "estblSmstrSctcd": "CMBS001400001",
            "estblGrade": "1",
            "sbjetSctnm": "\uc804\uacf5\uae30\ucd08",
            "sbjetNm": "\ub7ec\uc2dc\uc544\uc5b4\ubb38\ubc95 1",
            "sbjetDvnno": "002",
            "sbjetCd": "RUSS0316",
            "gubun": null,
            "pckgeRqstPssblYn": "N",
            "pckgeRqstCnt": "0",
            "name": null,
            "rmrk": null,
            "appcrCnt": "27",
            "attlcPrscpCnt": "30",
            "lssnsTimeInfo": "\ud654 7A,7B,8A<br/>\ubaa9 7A,7B,8A",
            "lssnsRealTimeInfo": "\ud654 15:00 ~ 16:30<br/>\ubaa9 15:00 ~ 16:30",
            "prctsTime": "0",
            "doPlan": "Kor",
            "thryTime": "3",
            "totalPrfssNm": "\uc11c\uad11\uc9c4",
            "mngetEstblYn": "Y",
            "code": null,
            "crdit": "3",
            "expniSllbsYn": "N",
            "bldngSn": null,
            "bldngCd": null,
            "bldngNm": null,
            "lssnsLcttmUntcd": null,
            "sbjetSctcd2": null,
            "rmnmCd": "203",
            "isApi": null,
            "paging": false,
            "rowStatus": "R",
            "pageSort": null
        },
        {
            "rowIndex": 0,
            "success": false,
            "message": null,
            "pageSize": 100,
            "pageNum": 1,
            "lctreMthodNm": "\ube44\ub300\uba74",
            "lctrmInfo": "\uc0ac\ud68c\uacfc\ud559\ub300\ud559",
            "lctreLnggeSctcd": null,
            "crseNo": "CLTR0082-001",
            "estblUnivNm": "\uc778\ubb38\ub300\ud559",
            "estblDprtnNm": "\ub178\uc5b4\ub178\ubb38\ud559\uacfc",
            "estblYear": "2022",
            "estblDprtnCd": "110B",
            "estblSmstrSctnm": "1\ud559\uae30",
            "estblSmstrSctcd": "CMBS001400001",
            "estblGrade": "1",
            "sbjetSctnm": "\uad50\uc591",
            "sbjetNm": "\ub9e4\uc2a4\ucef4\uacfc \uc0ac\ud68c",
            "sbjetDvnno": "001",
            "sbjetCd": "CLTR0082",
            "gubun": null,
            "pckgeRqstPssblYn": "N",
            "pckgeRqstCnt": "0",
            "name": null,
            "rmrk": null,
            "appcrCnt": "73",
            "attlcPrscpCnt": "70",
            "lssnsTimeInfo": "\ud654 5B,6A,6B<br/>\ubaa9 5B,6A,6B",
            "lssnsRealTimeInfo": "\ud654 13:30 ~ 15:00<br/>\ubaa9 13:30 ~ 15:00",
            "prctsTime": "0",
            "doPlan": "Kor",
            "thryTime": "3",
            "totalPrfssNm": "\uc870\uc131\ud638",
            "mngetEstblYn": "N",
            "code": null,
            "crdit": "3",
            "expniSllbsYn": "N",
            "bldngSn": null,
            "bldngCd": null,
            "bldngNm": null,
            "lssnsLcttmUntcd": null,
            "sbjetSctcd2": null,
            "rmnmCd": "101",
            "isApi": null,
            "paging": false,
            "rowStatus": "R",
            "pageSort": null
        },
        {
            "rowIndex": 0,
            "success": false,
            "message": null,
            "pageSize": 100,
            "pageNum": 1,
            "lctreMthodNm": "\ub300\uba74",
            "lctrmInfo": "\uc778\ubb38\ud55c\uad6d\uc9c4\ud765\uad00",
            "lctreLnggeSctcd": null,
            "crseNo": "RUSS0242-001",
            "estblUnivNm": "\uc778\ubb38\ub300\ud559",
            "estblDprtnNm": "\ub178\uc5b4\ub178\ubb38\ud559\uacfc",
            "estblYear": "2022",
            "estblDprtnCd": "110B",
            "estblSmstrSctnm": "1\ud559\uae30",
            "estblSmstrSctcd": "CMBS001400001",
            "estblGrade": "1",
            "sbjetSctnm": "\uc804\uacf5\uae30\ucd08",
            "sbjetNm": "\ub7ec\uc2dc\uc544\uc5b4 \uc74c\uc131\uc2e4\uc2b5",
            "sbjetDvnno": "001",
            "sbjetCd": "RUSS0242",
            "gubun": null,
            "pckgeRqstPssblYn": "N",
            "pckgeRqstCnt": "0",
            "name": null,
            "rmrk": "(\ub7ec\uc2dc\uc544\uc5b4)<br>",
            "appcrCnt": "30",
            "attlcPrscpCnt": "50",
            "lssnsTimeInfo": "\uc218 3A,3B<br/>\uc218 4A,4B",
            "lssnsRealTimeInfo": "\uc218 11:00 ~ 12:00<br/>\uc218 12:00 ~ 13:00",
            "prctsTime": "0",
            "doPlan": "Kor",
            "thryTime": "2",
            "totalPrfssNm": "\uc288\ud14c\ub974\ub2c8\ub098 \uc608\uce74\ud14c\ub9ac\ub098",
            "mngetEstblYn": "Y",
            "code": null,
            "crdit": "2",
            "expniSllbsYn": "N",
            "bldngSn": null,
            "bldngCd": null,
            "bldngNm": null,
            "lssnsLcttmUntcd": null,
            "sbjetSctcd2": null,
            "rmnmCd": "104",
            "isApi": null,
            "paging": false,
            "rowStatus": "R",
            "pageSort": null
        },
        {
            "rowIndex": 0,
            "success": false,
            "message": null,
            "pageSize": 100,
            "pageNum": 1,
            "lctreMthodNm": "\ub300\uba74",
            "lctrmInfo": "\uc778\ubb38\ud55c\uad6d\uc9c4\ud765\uad00",
            "lctreLnggeSctcd": null,
            "crseNo": "RUSS0325-001",
            "estblUnivNm": "\uc778\ubb38\ub300\ud559",
            "estblDprtnNm": "\ub178\uc5b4\ub178\ubb38\ud559\uacfc",
            "estblYear": "2022",
            "estblDprtnCd": "110B",
            "estblSmstrSctnm": "1\ud559\uae30",
            "estblSmstrSctcd": "CMBS001400001",
            "estblGrade": "2",
            "sbjetSctnm": "\uc804\uacf5\ud544\uc218",
            "sbjetNm": "\ub7ec\uc2dc\uc544 \uace0\uc804\uc758 \uc138\uacc4",
            "sbjetDvnno": "001",
            "sbjetCd": "RUSS0325",
            "gubun": null,
            "pckgeRqstPssblYn": "Y",
            "pckgeRqstCnt": "31",
            "name": null,
            "rmrk": null,
            "appcrCnt": "33",
            "attlcPrscpCnt": "50",
            "lssnsTimeInfo": "\ud654 5B,6A,6B<br/>\ubaa9 5B,6A,6B",
            "lssnsRealTimeInfo": "\ud654 13:30 ~ 15:00<br/>\ubaa9 13:30 ~ 15:00",
            "prctsTime": "0",
            "doPlan": "Kor",
            "thryTime": "3",
            "totalPrfssNm": "\uc774\ub300\uc6b0",
            "mngetEstblYn": "Y",
            "code": null,
            "crdit": "3",
            "expniSllbsYn": "N",
            "bldngSn": null,
            "bldngCd": null,
            "bldngNm": null,
            "lssnsLcttmUntcd": null,
            "sbjetSctcd2": null,
            "rmnmCd": "104",
            "isApi": null,
            "paging": false,
            "rowStatus": "R",
            "pageSort": null
        },
        {
            "rowIndex": 0,
            "success": false,
            "message": null,
            "pageSize": 100,
            "pageNum": 1,
            "lctreMthodNm": "\ub300\uba74",
            "lctrmInfo": "\ub300\ud559\uc6d0\ub3d9",
            "lctreLnggeSctcd": null,
            "crseNo": "RUSS0345-001",
            "estblUnivNm": "\uc778\ubb38\ub300\ud559",
            "estblDprtnNm": "\ub178\uc5b4\ub178\ubb38\ud559\uacfc",
            "estblYear": "2022",
            "estblDprtnCd": "110B",
            "estblSmstrSctnm": "1\ud559\uae30",
            "estblSmstrSctcd": "CMBS001400001",
            "estblGrade": "2",
            "sbjetSctnm": "\uc804\uacf5",
            "sbjetNm": "\ud604\ub300 \ub7ec\uc2dc\uc544 \uc0ac\ud68c\uc758 \uc774\ud574 1",
            "sbjetDvnno": "001",
            "sbjetCd": "RUSS0345",
            "gubun": null,
            "pckgeRqstPssblYn": "Y",
            "pckgeRqstCnt": "9",
            "name": null,
            "rmrk": "(\ub7ec\uc2dc\uc544\uc5b4)<br>",
            "appcrCnt": "12",
            "attlcPrscpCnt": "20",
            "lssnsTimeInfo": "\uc6d4 2B,3A,3B<br/>\uae08 1A,1B,2A",
            "lssnsRealTimeInfo": "\uc6d4 10:30 ~ 12:00<br/>\uae08 09:00 ~ 10:30",
            "prctsTime": "0",
            "doPlan": "Kor",
            "thryTime": "3",
            "totalPrfssNm": "\uc288\ud14c\ub974\ub2c8\ub098 \uc608\uce74\ud14c\ub9ac\ub098",
            "mngetEstblYn": "Y",
            "code": null,
            "crdit": "3",
            "expniSllbsYn": "N",
            "bldngSn": null,
            "bldngCd": null,
            "bldngNm": null,
            "lssnsLcttmUntcd": null,
            "sbjetSctcd2": null,
            "rmnmCd": "214",
            "isApi": null,
            "paging": false,
            "rowStatus": "R",
            "pageSort": null
        },
        {
            "rowIndex": 0,
            "success": false,
            "message": null,
            "pageSize": 100,
            "pageNum": 1,
            "lctreMthodNm": "\ub300\uba74",
            "lctrmInfo": "\uc778\ubb38\ub300\ud559",
            "lctreLnggeSctcd": null,
            "crseNo": "TCHR0480-001",
            "estblUnivNm": "\uc778\ubb38\ub300\ud559",
            "estblDprtnNm": "\ub178\uc5b4\ub178\ubb38\ud559\uacfc",
            "estblYear": "2022",
            "estblDprtnCd": "110B",
            "estblSmstrSctnm": "1\ud559\uae30",
            "estblSmstrSctcd": "CMBS001400001",
            "estblGrade": "3",
            "sbjetSctnm": "\uad50\uc9c1",
            "sbjetNm": "\ub7ec\uc2dc\uc544\uc5b4 \ub17c\ub9ac \ubc0f \ub17c\uc220\uc9c0\ub3c4",
            "sbjetDvnno": "001",
            "sbjetCd": "TCHR0480",
            "gubun": null,
            "pckgeRqstPssblYn": "Y",
            "pckgeRqstCnt": "4",
            "name": null,
            "rmrk": null,
            "appcrCnt": "4",
            "attlcPrscpCnt": "10",
            "lssnsTimeInfo": "\uc218 1A,1B,2A<br/>\uae08 2B,3A,3B",
            "lssnsRealTimeInfo": "\uc218 09:00 ~ 10:30<br/>\uae08 10:30 ~ 12:00",
            "prctsTime": "0",
            "doPlan": "Kor",
            "thryTime": "3",
            "totalPrfssNm": "\ubc15\ubbf8\uc815",
            "mngetEstblYn": "Y",
            "code": null,
            "crdit": "3",
            "expniSllbsYn": "N",
            "bldngSn": null,
            "bldngCd": null,
            "bldngNm": null,
            "lssnsLcttmUntcd": null,
            "sbjetSctcd2": null,
            "rmnmCd": "312",
            "isApi": null,
            "paging": false,
            "rowStatus": "R",
            "pageSort": null
        },
        {
            "rowIndex": 0,
            "success": false,
            "message": null,
            "pageSize": 100,
            "pageNum": 1,
            "lctreMthodNm": "\ud63c\ud569",
            "lctrmInfo": "\uc778\ubb38\ud55c\uad6d\uc9c4\ud765\uad00",
            "lctreLnggeSctcd": null,
            "crseNo": "CLTR0518-001",
            "estblUnivNm": "\uc778\ubb38\ub300\ud559",
            "estblDprtnNm": "\ub178\uc5b4\ub178\ubb38\ud559\uacfc",
            "estblYear": "2022",
            "estblDprtnCd": "110B",
            "estblSmstrSctnm": "1\ud559\uae30",
            "estblSmstrSctcd": "CMBS001400001",
            "estblGrade": "*",
            "sbjetSctnm": "\uad50\uc591",
            "sbjetNm": "\uc544\ub984\ub2e4\uc6c0\uc774\ub780 \ubb34\uc5c7\uc778\uac00",
            "sbjetDvnno": "001",
            "sbjetCd": "CLTR0518",
            "gubun": null,
            "pckgeRqstPssblYn": "Y",
            "pckgeRqstCnt": "78",
            "name": null,
            "rmrk": "\uc804\ud559\ub144\uc120\ud0dd<br>\ud50c\ub9bd\ub4dc\ub7ec\ub2dd\uac15\uc88c<br><b>\uc778\ubb38\uad50\uc591</b><br>",
            "appcrCnt": "73",
            "attlcPrscpCnt": "70",
            "lssnsTimeInfo": "\uc218 5B,6A,6B<br/>\uc218 7A,7B,8A",
            "lssnsRealTimeInfo": "\uc218 13:30 ~ 15:00<br/>\uc218 15:00 ~ 16:30",
            "prctsTime": "0",
            "doPlan": "Pre",
            "thryTime": "3",
            "totalPrfssNm": "\uc774\uac15\uc740",
            "mngetEstblYn": "Y",
            "code": null,
            "crdit": "3",
            "expniSllbsYn": "N",
            "bldngSn": null,
            "bldngCd": null,
            "bldngNm": null,
            "lssnsLcttmUntcd": null,
            "sbjetSctcd2": null,
            "rmnmCd": "104",
            "isApi": null,
            "paging": false,
            "rowStatus": "R",
            "pageSort": null
        },
        {
            "rowIndex": 0,
            "success": false,
            "message": null,
            "pageSize": 100,
            "pageNum": 1,
            "lctreMthodNm": "\ube44\ub300\uba74",
            "lctrmInfo": "\ub300\ud559\uc6d0\ub3d9",
            "lctreLnggeSctcd": null,
            "crseNo": "RUSS0422-001",
            "estblUnivNm": "\uc778\ubb38\ub300\ud559",
            "estblDprtnNm": "\ub178\uc5b4\ub178\ubb38\ud559\uacfc",
            "estblYear": "2022",
            "estblDprtnCd": "110B",
            "estblSmstrSctnm": "1\ud559\uae30",
            "estblSmstrSctcd": "CMBS001400001",
            "estblGrade": "3",
            "sbjetSctnm": "\uc804\uacf5",
            "sbjetNm": "\ub7ec\uc2dc\uc544\uc18c\uc124\ub860",
            "sbjetDvnno": "001",
            "sbjetCd": "RUSS0422",
            "gubun": null,
            "pckgeRqstPssblYn": "Y",
            "pckgeRqstCnt": "15",
            "name": null,
            "rmrk": "\uc6d0\uaca9\uac15\uc88c<br>",
            "appcrCnt": "41",
            "attlcPrscpCnt": "50",
            "lssnsTimeInfo": "\ud654 5B,6A,6B<br/>\ubaa9 5B,6A,6B",
            "lssnsRealTimeInfo": "\ud654 13:30 ~ 15:00<br/>\ubaa9 13:30 ~ 15:00",
            "prctsTime": "0",
            "doPlan": "Kor",
            "thryTime": "3",
            "totalPrfssNm": "\uc774\uac15\uc740",
            "mngetEstblYn": "Y",
            "code": null,
            "crdit": "3",
            "expniSllbsYn": "Y",
            "bldngSn": null,
            "bldngCd": null,
            "bldngNm": null,
            "lssnsLcttmUntcd": null,
            "sbjetSctcd2": null,
            "rmnmCd": "203",
            "isApi": null,
            "paging": false,
            "rowStatus": "R",
            "pageSort": null
        },
        {
            "rowIndex": 0,
            "success": false,
            "message": null,
            "pageSize": 100,
            "pageNum": 1,
            "lctreMthodNm": "\ube44\ub300\uba74",
            "lctrmInfo": "\uc778\ubb38\ud55c\uad6d\uc9c4\ud765\uad00",
            "lctreLnggeSctcd": null,
            "crseNo": "CLTR0508-001",
            "estblUnivNm": "\uc778\ubb38\ub300\ud559",
            "estblDprtnNm": "\ub178\uc5b4\ub178\ubb38\ud559\uacfc",
            "estblYear": "2022",
            "estblDprtnCd": "110B",
            "estblSmstrSctnm": "1\ud559\uae30",
            "estblSmstrSctcd": "CMBS001400001",
            "estblGrade": "*",
            "sbjetSctnm": "\uad50\uc591",
            "sbjetNm": "\uc778\uac04\uacfc \uc5b8\uc5b4",
            "sbjetDvnno": "001",
            "sbjetCd": "CLTR0508",
            "gubun": null,
            "pckgeRqstPssblYn": "Y",
            "pckgeRqstCnt": "94",
            "name": null,
            "rmrk": "\uc804\ud559\ub144\uc120\ud0dd<br><b>\uc778\ubb38\uad50\uc591</b><br>",
            "appcrCnt": "96",
            "attlcPrscpCnt": "95",
            "lssnsTimeInfo": "\ud654 1A,1B,2A<br/>\ubaa9 2B,3A,3B",
            "lssnsRealTimeInfo": "\ud654 09:00 ~ 10:30<br/>\ubaa9 10:30 ~ 12:00",
            "prctsTime": "0",
            "doPlan": "Kor",
            "thryTime": "3",
            "totalPrfssNm": "\uae40\uc815\uc77c",
            "mngetEstblYn": "Y",
            "code": null,
            "crdit": "3",
            "expniSllbsYn": "N",
            "bldngSn": null,
            "bldngCd": null,
            "bldngNm": null,
            "lssnsLcttmUntcd": null,
            "sbjetSctcd2": null,
            "rmnmCd": "104",
            "isApi": null,
            "paging": false,
            "rowStatus": "R",
            "pageSort": null
        },
        {
            "rowIndex": 0,
            "success": false,
            "message": null,
            "pageSize": 100,
            "pageNum": 1,
            "lctreMthodNm": "\ub300\uba74",
            "lctrmInfo": "\uc778\ubb38\ub300\ud559",
            "lctreLnggeSctcd": null,
            "crseNo": "RUSS0518-001",
            "estblUnivNm": "\uc778\ubb38\ub300\ud559",
            "estblDprtnNm": "\ub178\uc5b4\ub178\ubb38\ud559\uacfc",
            "estblYear": "2022",
            "estblDprtnCd": "110B",
            "estblSmstrSctnm": "1\ud559\uae30",
            "estblSmstrSctcd": "CMBS001400001",
            "estblGrade": "4",
            "sbjetSctnm": "\uc804\uacf5",
            "sbjetNm": "\ub7ec\uc2dc\uc544 \uc815\uce58\uc640 \uacbd\uc81c",
            "sbjetDvnno": "001",
            "sbjetCd": "RUSS0518",
            "gubun": null,
            "pckgeRqstPssblYn": "Y",
            "pckgeRqstCnt": "28",
            "name": null,
            "rmrk": null,
            "appcrCnt": "26",
            "attlcPrscpCnt": "50",
            "lssnsTimeInfo": "\ud654 1A,1B,2A<br/>\ubaa9 2B,3A,3B",
            "lssnsRealTimeInfo": "\ud654 09:00 ~ 10:30<br/>\ubaa9 10:30 ~ 12:00",
            "prctsTime": "0",
            "doPlan": "Kor",
            "thryTime": "3",
            "totalPrfssNm": "\uc774\uc0c1\ucca0",
            "mngetEstblYn": "Y",
            "code": null,
            "crdit": "3",
            "expniSllbsYn": "N",
            "bldngSn": null,
            "bldngCd": null,
            "bldngNm": null,
            "lssnsLcttmUntcd": null,
            "sbjetSctcd2": null,
            "rmnmCd": "101",
            "isApi": null,
            "paging": false,
            "rowStatus": "R",
            "pageSort": null
        },
        {
            "rowIndex": 0,
            "success": false,
            "message": null,
            "pageSize": 100,
            "pageNum": 1,
            "lctreMthodNm": "\ub300\uba74",
            "lctrmInfo": "\uc778\ubb38\ud55c\uad6d\uc9c4\ud765\uad00",
            "lctreLnggeSctcd": null,
            "crseNo": "CLTR0458-001",
            "estblUnivNm": "\uc778\ubb38\ub300\ud559",
            "estblDprtnNm": "\ub178\uc5b4\ub178\ubb38\ud559\uacfc",
            "estblYear": "2022",
            "estblDprtnCd": "110B",
            "estblSmstrSctnm": "1\ud559\uae30",
            "estblSmstrSctcd": "CMBS001400001",
            "estblGrade": "*",
            "sbjetSctnm": "\uad50\uc591",
            "sbjetNm": "\ub7ec\uc2dc\uc544 \ubb38\ud654 \uc77d\uae30",
            "sbjetDvnno": "001",
            "sbjetCd": "CLTR0458",
            "gubun": null,
            "pckgeRqstPssblYn": "Y",
            "pckgeRqstCnt": "74",
            "name": null,
            "rmrk": "\uc804\ud559\ub144\uc120\ud0dd<br><b>\uc778\ubb38\uad50\uc591</b><br>",
            "appcrCnt": "68",
            "attlcPrscpCnt": "70",
            "lssnsTimeInfo": "\uc6d4 2B,3A,3B<br/>\uae08 1A,1B,2A",
            "lssnsRealTimeInfo": "\uc6d4 10:30 ~ 12:00<br/>\uae08 09:00 ~ 10:30",
            "prctsTime": "0",
            "doPlan": "Kor",
            "thryTime": "3",
            "totalPrfssNm": "\uc774\uc0c1\ucca0",
            "mngetEstblYn": "Y",
            "code": null,
            "crdit": "3",
            "expniSllbsYn": "N",
            "bldngSn": null,
            "bldngCd": null,
            "bldngNm": null,
            "lssnsLcttmUntcd": null,
            "sbjetSctcd2": null,
            "rmnmCd": "104",
            "isApi": null,
            "paging": false,
            "rowStatus": "R",
            "pageSort": null
        },
        {
            "rowIndex": 0,
            "success": false,
            "message": null,
            "pageSize": 100,
            "pageNum": 1,
            "lctreMthodNm": "\ub300\uba74",
            "lctrmInfo": "\ub300\ud559\uc6d0\ub3d9",
            "lctreLnggeSctcd": null,
            "crseNo": "RUSS0224-001",
            "estblUnivNm": "\uc778\ubb38\ub300\ud559",
            "estblDprtnNm": "\ub178\uc5b4\ub178\ubb38\ud559\uacfc",
            "estblYear": "2022",
            "estblDprtnCd": "110B",
            "estblSmstrSctnm": "1\ud559\uae30",
            "estblSmstrSctcd": "CMBS001400001",
            "estblGrade": "1",
            "sbjetSctnm": "\uc804\uacf5\uae30\ucd08",
            "sbjetNm": "\ub7ec\uc2dc\uc544\uc5b4\ubb38\ubc95\ud65c\uc6a91",
            "sbjetDvnno": "001",
            "sbjetCd": "RUSS0224",
            "gubun": null,
            "pckgeRqstPssblYn": "N",
            "pckgeRqstCnt": "0",
            "name": null,
            "rmrk": null,
            "appcrCnt": "33",
            "attlcPrscpCnt": "50",
            "lssnsTimeInfo": "\uc218 6A,6B<br/>\uc218 7A,7B",
            "lssnsRealTimeInfo": "\uc218 14:00 ~ 15:00<br/>\uc218 15:00 ~ 16:00",
            "prctsTime": "0",
            "doPlan": "Kor",
            "thryTime": "2",
            "totalPrfssNm": "\uae40\ub098\uc601",
            "mngetEstblYn": "Y",
            "code": null,
            "crdit": "2",
            "expniSllbsYn": "N",
            "bldngSn": null,
            "bldngCd": null,
            "bldngNm": null,
            "lssnsLcttmUntcd": null,
            "sbjetSctcd2": null,
            "rmnmCd": "203",
            "isApi": null,
            "paging": false,
            "rowStatus": "R",
            "pageSort": null
        },
        {
            "rowIndex": 0,
            "success": false,
            "message": null,
            "pageSize": 100,
            "pageNum": 1,
            "lctreMthodNm": "\ud63c\ud569",
            "lctrmInfo": "\ub300\ud559\uc6d0\ub3d9",
            "lctreLnggeSctcd": null,
            "crseNo": "RUSS0318-001",
            "estblUnivNm": "\uc778\ubb38\ub300\ud559",
            "estblDprtnNm": "\ub178\uc5b4\ub178\ubb38\ud559\uacfc",
            "estblYear": "2022",
            "estblDprtnCd": "110B",
            "estblSmstrSctnm": "1\ud559\uae30",
            "estblSmstrSctcd": "CMBS001400001",
            "estblGrade": "2",
            "sbjetSctnm": "\uc804\uacf5\ud544\uc218",
            "sbjetNm": "\ub7ec\uc2dc\uc544\uc5b4\ubb38\ubc95 3",
            "sbjetDvnno": "001",
            "sbjetCd": "RUSS0318",
            "gubun": null,
            "pckgeRqstPssblYn": "Y",
            "pckgeRqstCnt": "59",
            "name": null,
            "rmrk": null,
            "appcrCnt": "65",
            "attlcPrscpCnt": "65",
            "lssnsTimeInfo": "\uc6d4 8B,9A,9B<br/>\uc218 7A,7B,8A",
            "lssnsRealTimeInfo": "\uc6d4 16:30 ~ 18:00<br/>\uc218 15:00 ~ 16:30",
            "prctsTime": "0",
            "doPlan": "Kor",
            "thryTime": "3",
            "totalPrfssNm": "\uae40\uc815\uc77c",
            "mngetEstblYn": "Y",
            "code": null,
            "crdit": "3",
            "expniSllbsYn": "N",
            "bldngSn": null,
            "bldngCd": null,
            "bldngNm": null,
            "lssnsLcttmUntcd": null,
            "sbjetSctcd2": null,
            "rmnmCd": "214",
            "isApi": null,
            "paging": false,
            "rowStatus": "R",
            "pageSort": null
        },
        {
            "rowIndex": 0,
            "success": false,
            "message": null,
            "pageSize": 100,
            "pageNum": 1,
            "lctreMthodNm": "\ub300\uba74",
            "lctrmInfo": "\uc778\ubb38\ud55c\uad6d\uc9c4\ud765\uad00",
            "lctreLnggeSctcd": null,
            "crseNo": "RUSS0334-001",
            "estblUnivNm": "\uc778\ubb38\ub300\ud559",
            "estblDprtnNm": "\ub178\uc5b4\ub178\ubb38\ud559\uacfc",
            "estblYear": "2022",
            "estblDprtnCd": "110B",
            "estblSmstrSctnm": "1\ud559\uae30",
            "estblSmstrSctcd": "CMBS001400001",
            "estblGrade": "2",
            "sbjetSctnm": "\uc804\uacf5\uae30\ucd08",
            "sbjetNm": "\ub7ec\uc2dc\uc544\uc5b4 \uac15\ub3c51",
            "sbjetDvnno": "001",
            "sbjetCd": "RUSS0334",
            "gubun": null,
            "pckgeRqstPssblYn": "Y",
            "pckgeRqstCnt": "29",
            "name": null,
            "rmrk": null,
            "appcrCnt": "21",
            "attlcPrscpCnt": "50",
            "lssnsTimeInfo": "\uc218 8B,9A,9B<br/>\uae08 8B,9A,9B",
            "lssnsRealTimeInfo": "\uc218 16:30 ~ 18:00<br/>\uae08 16:30 ~ 18:00",
            "prctsTime": "0",
            "doPlan": "Kor",
            "thryTime": "3",
            "totalPrfssNm": "\uc11c\uad11\uc9c4",
            "mngetEstblYn": "Y",
            "code": null,
            "crdit": "3",
            "expniSllbsYn": "N",
            "bldngSn": null,
            "bldngCd": null,
            "bldngNm": null,
            "lssnsLcttmUntcd": null,
            "sbjetSctcd2": null,
            "rmnmCd": "104",
            "isApi": null,
            "paging": false,
            "rowStatus": "R",
            "pageSort": null
        },
        {
            "rowIndex": 0,
            "success": false,
            "message": null,
            "pageSize": 100,
            "pageNum": 1,
            "lctreMthodNm": "\ub300\uba74",
            "lctrmInfo": "\ub300\ud559\uc6d0\ub3d9",
            "lctreLnggeSctcd": null,
            "crseNo": "RUSS0445-001",
            "estblUnivNm": "\uc778\ubb38\ub300\ud559",
            "estblDprtnNm": "\ub178\uc5b4\ub178\ubb38\ud559\uacfc",
            "estblYear": "2022",
            "estblDprtnCd": "110B",
            "estblSmstrSctnm": "1\ud559\uae30",
            "estblSmstrSctcd": "CMBS001400001",
            "estblGrade": "3",
            "sbjetSctnm": "\uc804\uacf5",
            "sbjetNm": "\uace0\uae09 \ub7ec\uc2dc\uc544\uc5b4 \ud68c\ud654",
            "sbjetDvnno": "001",
            "sbjetCd": "RUSS0445",
            "gubun": null,
            "pckgeRqstPssblYn": "Y",
            "pckgeRqstCnt": "20",
            "name": null,
            "rmrk": "(\ub7ec\uc2dc\uc544\uc5b4)<br>",
            "appcrCnt": "16",
            "attlcPrscpCnt": "50",
            "lssnsTimeInfo": "\uc6d4 7A,7B,8A<br/>\uae08 7A,7B,8A",
            "lssnsRealTimeInfo": "\uc6d4 15:00 ~ 16:30<br/>\uae08 15:00 ~ 16:30",
            "prctsTime": "0",
            "doPlan": "Kor",
            "thryTime": "3",
            "totalPrfssNm": "\uc288\ud14c\ub974\ub2c8\ub098 \uc608\uce74\ud14c\ub9ac\ub098",
            "mngetEstblYn": "Y",
            "code": null,
            "crdit": "3",
            "expniSllbsYn": "Y",
            "bldngSn": null,
            "bldngCd": null,
            "bldngNm": null,
            "lssnsLcttmUntcd": null,
            "sbjetSctcd2": null,
            "rmnmCd": "203",
            "isApi": null,
            "paging": false,
            "rowStatus": "R",
            "pageSort": null
        },
        {
            "rowIndex": 0,
            "success": false,
            "message": null,
            "pageSize": 100,
            "pageNum": 1,
            "lctreMthodNm": "\ub300\uba74",
            "lctrmInfo": "\uc778\ubb38\ud55c\uad6d\uc9c4\ud765\uad00",
            "lctreLnggeSctcd": null,
            "crseNo": "CLTR0132-001",
            "estblUnivNm": "\uc778\ubb38\ub300\ud559",
            "estblDprtnNm": "\ub178\uc5b4\ub178\ubb38\ud559\uacfc",
            "estblYear": "2022",
            "estblDprtnCd": "110B",
            "estblSmstrSctnm": "1\ud559\uae30",
            "estblSmstrSctcd": "CMBS001400001",
            "estblGrade": "1",
            "sbjetSctnm": "\uad50\uc591",
            "sbjetNm": "\ub7ec\uc2dc\uc544\ubb38\ud559\uc758 \uc774\ud574",
            "sbjetDvnno": "001",
            "sbjetCd": "CLTR0132",
            "gubun": null,
            "pckgeRqstPssblYn": "N",
            "pckgeRqstCnt": "0",
            "name": null,
            "rmrk": "<b>\uc778\ubb38\uad50\uc591</b><br>",
            "appcrCnt": "36",
            "attlcPrscpCnt": "70",
            "lssnsTimeInfo": "\ud654 8B,9A,9B<br/>\ubaa9 8B,9A,9B",
            "lssnsRealTimeInfo": "\ud654 16:30 ~ 18:00<br/>\ubaa9 16:30 ~ 18:00",
            "prctsTime": "0",
            "doPlan": "Kor",
            "thryTime": "3",
            "totalPrfssNm": "\uc11c\uad11\uc9c4",
            "mngetEstblYn": "Y",
            "code": null,
            "crdit": "3",
            "expniSllbsYn": "Y",
            "bldngSn": null,
            "bldngCd": null,
            "bldngNm": null,
            "lssnsLcttmUntcd": null,
            "sbjetSctcd2": null,
            "rmnmCd": "104",
            "isApi": null,
            "paging": false,
            "rowStatus": "R",
            "pageSort": null
        },
        {
            "rowIndex": 0,
            "success": false,
            "message": null,
            "pageSize": 100,
            "pageNum": 1,
            "lctreMthodNm": "\ub300\uba74",
            "lctrmInfo": "\ub300\ud559\uc6d0\ub3d9",
            "lctreLnggeSctcd": null,
            "crseNo": "RUSS0506-001",
            "estblUnivNm": "\uc778\ubb38\ub300\ud559",
            "estblDprtnNm": "\ub178\uc5b4\ub178\ubb38\ud559\uacfc",
            "estblYear": "2022",
            "estblDprtnCd": "110B",
            "estblSmstrSctnm": "1\ud559\uae30",
            "estblSmstrSctcd": "CMBS001400001",
            "estblGrade": "3",
            "sbjetSctnm": "\uc804\uacf5",
            "sbjetNm": "\ub7ec\uc2dc\uc544\uc9c0\uc5ed\ud559\uac1c\ub860",
            "sbjetDvnno": "001",
            "sbjetCd": "RUSS0506",
            "gubun": null,
            "pckgeRqstPssblYn": "Y",
            "pckgeRqstCnt": "24",
            "name": null,
            "rmrk": null,
            "appcrCnt": "28",
            "attlcPrscpCnt": "50",
            "lssnsTimeInfo": "\ud654 8B,9A,9B<br/>\ubaa9 8B,9A,9B",
            "lssnsRealTimeInfo": "\ud654 16:30 ~ 18:00<br/>\ubaa9 16:30 ~ 18:00",
            "prctsTime": "0",
            "doPlan": "Kor",
            "thryTime": "3",
            "totalPrfssNm": "\uc774\ub300\uc6b0",
            "mngetEstblYn": "Y",
            "code": null,
            "crdit": "3",
            "expniSllbsYn": "N",
            "bldngSn": null,
            "bldngCd": null,
            "bldngNm": null,
            "lssnsLcttmUntcd": null,
            "sbjetSctcd2": null,
            "rmnmCd": "203",
            "isApi": null,
            "paging": false,
            "rowStatus": "R",
            "pageSort": null
        },
        {
            "rowIndex": 0,
            "success": false,
            "message": null,
            "pageSize": 100,
            "pageNum": 1,
            "lctreMthodNm": "\ub300\uba74",
            "lctrmInfo": "\uc778\ubb38\ub300\ud559",
            "lctreLnggeSctcd": null,
            "crseNo": "RUSS0507-001",
            "estblUnivNm": "\uc778\ubb38\ub300\ud559",
            "estblDprtnNm": "\ub178\uc5b4\ub178\ubb38\ud559\uacfc",
            "estblYear": "2022",
            "estblDprtnCd": "110B",
            "estblSmstrSctnm": "1\ud559\uae30",
            "estblSmstrSctcd": "CMBS001400001",
            "estblGrade": "3",
            "sbjetSctnm": "\uc804\uacf5",
            "sbjetNm": "\uadf9\ub3d9 \uc9c0\uc5ed \uc5f0\uad6c",
            "sbjetDvnno": "001",
            "sbjetCd": "RUSS0507",
            "gubun": null,
            "pckgeRqstPssblYn": "Y",
            "pckgeRqstCnt": "11",
            "name": null,
            "rmrk": null,
            "appcrCnt": "10",
            "attlcPrscpCnt": "50",
            "lssnsTimeInfo": "\uc6d4 5B,6A,6B<br/>\uae08 5B,6A,6B",
            "lssnsRealTimeInfo": "\uc6d4 13:30 ~ 15:00<br/>\uae08 13:30 ~ 15:00",
            "prctsTime": "0",
            "doPlan": "Kor",
            "thryTime": "3",
            "totalPrfssNm": "\ubc15\uc885\uad00",
            "mngetEstblYn": "Y",
            "code": null,
            "crdit": "3",
            "expniSllbsYn": "Y",
            "bldngSn": null,
            "bldngCd": null,
            "bldngNm": null,
            "lssnsLcttmUntcd": null,
            "sbjetSctcd2": null,
            "rmnmCd": "312",
            "isApi": null,
            "paging": false,
            "rowStatus": "R",
            "pageSort": null
        },
        {
            "rowIndex": 0,
            "success": false,
            "message": null,
            "pageSize": 100,
            "pageNum": 1,
            "lctreMthodNm": "\ube44\ub300\uba74",
            "lctrmInfo": "\uc778\ubb38\ud55c\uad6d\uc9c4\ud765\uad00",
            "lctreLnggeSctcd": null,
            "crseNo": "CLTR0255-001",
            "estblUnivNm": "\uc778\ubb38\ub300\ud559",
            "estblDprtnNm": "\ub178\uc5b4\ub178\ubb38\ud559\uacfc",
            "estblYear": "2022",
            "estblDprtnCd": "110B",
            "estblSmstrSctnm": "1\ud559\uae30",
            "estblSmstrSctcd": "CMBS001400001",
            "estblGrade": "*",
            "sbjetSctnm": "\uad50\uc591",
            "sbjetNm": "SciArt \ub4e4\uc5ec\ub2e4\ubcf4\uae30",
            "sbjetDvnno": "001",
            "sbjetCd": "CLTR0255",
            "gubun": null,
            "pckgeRqstPssblYn": "Y",
            "pckgeRqstCnt": "12",
            "name": null,
            "rmrk": "\uc804\ud559\ub144\uc120\ud0dd<br>\ud6c4\ubc18\ubd80 \uac15\uc758 \uc2e0\uaddc \uac15\uc0ac \ub2f4\ub2f9 \uc608\uc815 ",
            "appcrCnt": "70",
            "attlcPrscpCnt": "70",
            "lssnsTimeInfo": "\uc218 1A,1B,2A<br/>\uae08 2B,3A,3B",
            "lssnsRealTimeInfo": "\uc218 09:00 ~ 10:30<br/>\uae08 10:30 ~ 12:00",
            "prctsTime": "0",
            "doPlan": "Kor",
            "thryTime": "3",
            "totalPrfssNm": "\ubc31\uacbd\ud76c<br/>\uc774\ub300\uc6b0",
            "mngetEstblYn": "Y",
            "code": null,
            "crdit": "3",
            "expniSllbsYn": "N",
            "bldngSn": null,
            "bldngCd": null,
            "bldngNm": null,
            "lssnsLcttmUntcd": null,
            "sbjetSctcd2": null,
            "rmnmCd": "104",
            "isApi": null,
            "paging": false,
            "rowStatus": "R",
            "pageSort": null
        },
        {
            "rowIndex": 0,
            "success": false,
            "message": null,
            "pageSize": 100,
            "pageNum": 1,
            "lctreMthodNm": "\ub300\uba74",
            "lctrmInfo": "\ub300\ud559\uc6d0\ub3d9",
            "lctreLnggeSctcd": null,
            "crseNo": "RUSS0345-002",
            "estblUnivNm": "\uc778\ubb38\ub300\ud559",
            "estblDprtnNm": "\ub178\uc5b4\ub178\ubb38\ud559\uacfc",
            "estblYear": "2022",
            "estblDprtnCd": "110B",
            "estblSmstrSctnm": "1\ud559\uae30",
            "estblSmstrSctcd": "CMBS001400001",
            "estblGrade": "2",
            "sbjetSctnm": "\uc804\uacf5",
            "sbjetNm": "\ud604\ub300 \ub7ec\uc2dc\uc544 \uc0ac\ud68c\uc758 \uc774\ud574 1",
            "sbjetDvnno": "002",
            "sbjetCd": "RUSS0345",
            "gubun": null,
            "pckgeRqstPssblYn": "Y",
            "pckgeRqstCnt": "26",
            "name": null,
            "rmrk": "(\ub7ec\uc2dc\uc544\uc5b4)<br>",
            "appcrCnt": "21",
            "attlcPrscpCnt": "20",
            "lssnsTimeInfo": "\uc218 1A,1B,2A<br/>\uae08 2B,3A,3B",
            "lssnsRealTimeInfo": "\uc218 09:00 ~ 10:30<br/>\uae08 10:30 ~ 12:00",
            "prctsTime": "0",
            "doPlan": "Kor",
            "thryTime": "3",
            "totalPrfssNm": "\uc288\ud14c\ub974\ub2c8\ub098 \uc608\uce74\ud14c\ub9ac\ub098",
            "mngetEstblYn": "Y",
            "code": null,
            "crdit": "3",
            "expniSllbsYn": "N",
            "bldngSn": null,
            "bldngCd": null,
            "bldngNm": null,
            "lssnsLcttmUntcd": null,
            "sbjetSctcd2": null,
            "rmnmCd": "214",
            "isApi": null,
            "paging": false,
            "rowStatus": "R",
            "pageSort": null
        },
        {
            "rowIndex": 0,
            "success": false,
            "message": null,
            "pageSize": 100,
            "pageNum": 1,
            "lctreMthodNm": "\ub300\uba74",
            "lctrmInfo": "\ub300\ud559\uc6d0\ub3d9",
            "lctreLnggeSctcd": null,
            "crseNo": "CLTR0036-001",
            "estblUnivNm": "\uc778\ubb38\ub300\ud559",
            "estblDprtnNm": "\ub178\uc5b4\ub178\ubb38\ud559\uacfc",
            "estblYear": "2022",
            "estblDprtnCd": "110B",
            "estblSmstrSctnm": "1\ud559\uae30",
            "estblSmstrSctcd": "CMBS001400001",
            "estblGrade": "1",
            "sbjetSctnm": "\uad50\uc591",
            "sbjetNm": "\ub7ec\uc2dc\uc544\uc5b4 I",
            "sbjetDvnno": "001",
            "sbjetCd": "CLTR0036",
            "gubun": null,
            "pckgeRqstPssblYn": "N",
            "pckgeRqstCnt": "0",
            "name": null,
            "rmrk": "<b>\uc778\ubb38\uad50\uc591</b><br>",
            "appcrCnt": "29",
            "attlcPrscpCnt": "50",
            "lssnsTimeInfo": "\uc218 8B,9A,9B<br/>\uae08 8B,9A,9B",
            "lssnsRealTimeInfo": "\uc218 16:30 ~ 18:00<br/>\uae08 16:30 ~ 18:00",
            "prctsTime": "0",
            "doPlan": "Kor",
            "thryTime": "3",
            "totalPrfssNm": "\uc774\ub300\uc6b0",
            "mngetEstblYn": "Y",
            "code": null,
            "crdit": "3",
            "expniSllbsYn": "N",
            "bldngSn": null,
            "bldngCd": null,
            "bldngNm": null,
            "lssnsLcttmUntcd": null,
            "sbjetSctcd2": null,
            "rmnmCd": "203",
            "isApi": null,
            "paging": false,
            "rowStatus": "R",
            "pageSort": null
        },
        {
            "rowIndex": 0,
            "success": false,
            "message": null,
            "pageSize": 100,
            "pageNum": 1,
            "lctreMthodNm": "\ub300\uba74",
            "lctrmInfo": "\ub300\ud559\uc6d0\ub3d9",
            "lctreLnggeSctcd": null,
            "crseNo": "RUSS0524-001",
            "estblUnivNm": "\uc778\ubb38\ub300\ud559",
            "estblDprtnNm": "\ub178\uc5b4\ub178\ubb38\ud559\uacfc",
            "estblYear": "2022",
            "estblDprtnCd": "110B",
            "estblSmstrSctnm": "1\ud559\uae30",
            "estblSmstrSctcd": "CMBS001400001",
            "estblGrade": "4",
            "sbjetSctnm": "\uc804\uacf5",
            "sbjetNm": "\ub7ec\uc2dc\uc544\ud76c\uace1",
            "sbjetDvnno": "001",
            "sbjetCd": "RUSS0524",
            "gubun": null,
            "pckgeRqstPssblYn": "Y",
            "pckgeRqstCnt": "5",
            "name": null,
            "rmrk": null,
            "appcrCnt": "3",
            "attlcPrscpCnt": "50",
            "lssnsTimeInfo": "\uc6d4 2B,3A,3B<br/>\uae08 1A,1B,2A",
            "lssnsRealTimeInfo": "\uc6d4 10:30 ~ 12:00<br/>\uae08 09:00 ~ 10:30",
            "prctsTime": "0",
            "doPlan": "Kor",
            "thryTime": "3",
            "totalPrfssNm": "\uae40\uaddc\uc885",
            "mngetEstblYn": "Y",
            "code": null,
            "crdit": "3",
            "expniSllbsYn": "Y",
            "bldngSn": null,
            "bldngCd": null,
            "bldngNm": null,
            "lssnsLcttmUntcd": null,
            "sbjetSctcd2": null,
            "rmnmCd": "203",
            "isApi": null,
            "paging": false,
            "rowStatus": "R",
            "pageSort": null
        },
        {
            "rowIndex": 0,
            "success": false,
            "message": null,
            "pageSize": 100,
            "pageNum": 1,
            "lctreMthodNm": "\ub300\uba74",
            "lctrmInfo": "\uc778\ubb38\ud55c\uad6d\uc9c4\ud765\uad00",
            "lctreLnggeSctcd": null,
            "crseNo": "TCHR0591-001",
            "estblUnivNm": "\uc778\ubb38\ub300\ud559",
            "estblDprtnNm": "\ub178\uc5b4\ub178\ubb38\ud559\uacfc",
            "estblYear": "2022",
            "estblDprtnCd": "110B",
            "estblSmstrSctnm": "1\ud559\uae30",
            "estblSmstrSctcd": "CMBS001400001",
            "estblGrade": "3",
            "sbjetSctnm": "\uad50\uc9c1",
            "sbjetNm": "\ub7ec\uc2dc\uc544\uc5b4\uad50\uc721\ub860",
            "sbjetDvnno": "001",
            "sbjetCd": "TCHR0591",
            "gubun": null,
            "pckgeRqstPssblYn": "Y",
            "pckgeRqstCnt": "1",
            "name": null,
            "rmrk": "2022\ud559\ub144\ub3c4 \uc2e0\uaddc \uc784\uc6a9 \uac15\uc0ac \ubc30\uc815 \uc608\uc815",
            "appcrCnt": "1",
            "attlcPrscpCnt": "10",
            "lssnsTimeInfo": "\ud654 1A,1B,2A<br/>\ubaa9 2B,3A,3B",
            "lssnsRealTimeInfo": "\ud654 09:00 ~ 10:30<br/>\ubaa9 10:30 ~ 12:00",
            "prctsTime": "0",
            "doPlan": "Kor",
            "thryTime": "3",
            "totalPrfssNm": "\ubc31\uacbd\ud76c",
            "mngetEstblYn": "Y",
            "code": null,
            "crdit": "3",
            "expniSllbsYn": "N",
            "bldngSn": null,
            "bldngCd": null,
            "bldngNm": null,
            "lssnsLcttmUntcd": null,
            "sbjetSctcd2": null,
            "rmnmCd": "213",
            "isApi": null,
            "paging": false,
            "rowStatus": "R",
            "pageSort": null
        },
        {
            "rowIndex": 0,
            "success": false,
            "message": null,
            "pageSize": 100,
            "pageNum": 1,
            "lctreMthodNm": "\ub300\uba74",
            "lctrmInfo": "\ub300\ud559\uc6d0\ub3d9",
            "lctreLnggeSctcd": null,
            "crseNo": "RUSS0316-001",
            "estblUnivNm": "\uc778\ubb38\ub300\ud559",
            "estblDprtnNm": "\ub178\uc5b4\ub178\ubb38\ud559\uacfc",
            "estblYear": "2022",
            "estblDprtnCd": "110B",
            "estblSmstrSctnm": "1\ud559\uae30",
            "estblSmstrSctcd": "CMBS001400001",
            "estblGrade": "1",
            "sbjetSctnm": "\uc804\uacf5\uae30\ucd08",
            "sbjetNm": "\ub7ec\uc2dc\uc544\uc5b4\ubb38\ubc95 1",
            "sbjetDvnno": "001",
            "sbjetCd": "RUSS0316",
            "gubun": null,
            "pckgeRqstPssblYn": "N",
            "pckgeRqstCnt": "0",
            "name": null,
            "rmrk": null,
            "appcrCnt": "16",
            "attlcPrscpCnt": "30",
            "lssnsTimeInfo": "\ud654 2B,3A,3B<br/>\ubaa9 1A,1B,2A",
            "lssnsRealTimeInfo": "\ud654 10:30 ~ 12:00<br/>\ubaa9 09:00 ~ 10:30",
            "prctsTime": "0",
            "doPlan": "Kor",
            "thryTime": "3",
            "totalPrfssNm": "\uae40\uc815\uc77c",
            "mngetEstblYn": "Y",
            "code": null,
            "crdit": "3",
            "expniSllbsYn": "N",
            "bldngSn": null,
            "bldngCd": null,
            "bldngNm": null,
            "lssnsLcttmUntcd": null,
            "sbjetSctcd2": null,
            "rmnmCd": "214",
            "isApi": null,
            "paging": false,
            "rowStatus": "R",
            "pageSort": null
        },
        {
            "rowIndex": 0,
            "success": false,
            "message": null,
            "pageSize": 100,
            "pageNum": 1,
            "lctreMthodNm": "\ub300\uba74",
            "lctrmInfo": "\ub300\ud559\uc6d0\ub3d9",
            "lctreLnggeSctcd": null,
            "crseNo": "RUSS0414-001",
            "estblUnivNm": "\uc778\ubb38\ub300\ud559",
            "estblDprtnNm": "\ub178\uc5b4\ub178\ubb38\ud559\uacfc",
            "estblYear": "2022",
            "estblDprtnCd": "110B",
            "estblSmstrSctnm": "1\ud559\uae30",
            "estblSmstrSctcd": "CMBS001400001",
            "estblGrade": "3",
            "sbjetSctnm": "\uc804\uacf5\ud544\uc218",
            "sbjetNm": "\ub7ec\uc2dc\uc544\uc5b4 \ud615\ud0dc\ub860",
            "sbjetDvnno": "001",
            "sbjetCd": "RUSS0414",
            "gubun": null,
            "pckgeRqstPssblYn": "Y",
            "pckgeRqstCnt": "28",
            "name": null,
            "rmrk": null,
            "appcrCnt": "35",
            "attlcPrscpCnt": "50",
            "lssnsTimeInfo": "\ud654 7A,7B,8A<br/>\ubaa9 7A,7B,8A",
            "lssnsRealTimeInfo": "\ud654 15:00 ~ 16:30<br/>\ubaa9 15:00 ~ 16:30",
            "prctsTime": "0",
            "doPlan": "Kor",
            "thryTime": "3",
            "totalPrfssNm": "\uae40\uc815\uc77c",
            "mngetEstblYn": "Y",
            "code": null,
            "crdit": "3",
            "expniSllbsYn": "N",
            "bldngSn": null,
            "bldngCd": null,
            "bldngNm": null,
            "lssnsLcttmUntcd": null,
            "sbjetSctcd2": null,
            "rmnmCd": "214",
            "isApi": null,
            "paging": false,
            "rowStatus": "R",
            "pageSort": null
        }
    ],
    "statusCode": 200
}